Workbook

Sheet Data
A1: date | B1: description | C1: price | D1: quantity | E1: total | F1: category | G1: product | H1: year | I1: month | J1: profit
A2: 45292 | B2: amortization | C2: NA | D2: NA | E2: 50 | F2: =IFERROR(LEFT(B2,FIND(":",B2)-1),B2) -> amortization | G2: NA | H2: =YEAR(A2) -> 2024 | I2: =MONTH(A2) -> 1 | J2: =IF(F2="net sales",E2, IF(F2="cogs",-E2, IF(OR(F2="marketing",F2="overhead",F2="payroll",F2="interest","amortization"),-E2,0))) -> 0
A3: 45292 | B3: cogs:product 1 | C3: 5.99 | D3: 71 | E3: 425.29 | F3: =IFERROR(LEFT(B3,FIND(":",B3)-1),B3) -> cogs | G3: =IFERROR(RIGHT(B3,LEN(B3)-FIND(":",B3)),"") -> product 1 | H3: =YEAR(A3) -> 2024 | I3: =MONTH(A3) -> 1 | J3: =IF(F3="net sales",E3, IF(F3="cogs",-E3, IF(OR(F3="marketing",F3="overhead",F3="payroll",F3="interest","amortization"),-E3,0))) -> -425.29
A4: 45292 | B4: cogs:product 2 | C4: 16.99 | D4: 3 | E4: 50.97 | F4: =IFERROR(LEFT(B4,FIND(":",B4)-1),B4) -> cogs | G4: =IFERROR(RIGHT(B4,LEN(B4)-FIND(":",B4)),"") -> product 2 | H4: =YEAR(A4) -> 2024 | I4: =MONTH(A4) -> 1 | J4: =IF(F4="net sales",E4, IF(F4="cogs",-E4, IF(OR(F4="marketing",F4="overhead",F4="payroll",F4="interest","amortization"),-E4,0))) -> -50.97
A5: 45292 | B5: cogs:product 3 | C5: 8.49 | D5: 78 | E5: 662.22 | F5: =IFERROR(LEFT(B5,FIND(":",B5)-1),B5) -> cogs | G5: =IFERROR(RIGHT(B5,LEN(B5)-FIND(":",B5)),"") -> product 3 | H5: =YEAR(A5) -> 2024 | I5: =MONTH(A5) -> 1 | J5: =IF(F5="net sales",E5, IF(F5="cogs",-E5, IF(OR(F5="marketing",F5="overhead",F5="payroll",F5="interest","amortization"),-E5,0))) -> -662.22
A6: 45292 | B6: marketing | C6: NA | D6: NA | E6: 99.99 | F6: =IFERROR(LEFT(B6,FIND(":",B6)-1),B6) -> marketing | G6: NA | H6: =YEAR(A6) -> 2024 | I6: =MONTH(A6) -> 1 | J6: =IF(F6="net sales",E6, IF(F6="cogs",-E6, IF(OR(F6="marketing",F6="overhead",F6="payroll",F6="interest","amortization"),-E6,0))) -> -99.99
A7: 45292 | B7: net sales:product 1 | C7: 9.99 | D7: 71 | E7: 709.29 | F7: =IFERROR(LEFT(B7,FIND(":",B7)-1),B7) -> net sales | G7: =IFERROR(RIGHT(B7,LEN(B7)-FIND(":",B7)),"") -> product 1 | H7: =YEAR(A7) -> 2024 | I7: =MONTH(A7) -> 1 | J7: =IF(F7="net sales",E7, IF(F7="cogs",-E7, IF(OR(F7="marketing",F7="overhead",F7="payroll",F7="interest","amortization"),-E7,0))) -> 709.29
A8: 45292 | B8: net sales:product 2 | C8: 24.99 | D8: 3 | E8: 74.97 | F8: =IFERROR(LEFT(B8,FIND(":",B8)-1),B8) -> net sales | G8: =IFERROR(RIGHT(B8,LEN(B8)-FIND(":",B8)),"") -> product 2 | H8: =YEAR(A8) -> 2024 | I8: =MONTH(A8) -> 1 | J8: =IF(F8="net sales",E8, IF(F8="cogs",-E8, IF(OR(F8="marketing",F8="overhead",F8="payroll",F8="interest","amortization"),-E8,0))) -> 74.97
A9: 45292 | B9: net sales:product 3 | C9: 12.49 | D9: 78 | E9: 974.22 | F9: =IFERROR(LEFT(B9,FIND(":",B9)-1),B9) -> net sales | G9: =IFERROR(RIGHT(B9,LEN(B9)-FIND(":",B9)),"") -> product 3 | H9: =YEAR(A9) -> 2024 | I9: =MONTH(A9) -> 1 | J9: =IF(F9="net sales",E9, IF(F9="cogs",-E9, IF(OR(F9="marketing",F9="overhead",F9="payroll",F9="interest","amortization"),-E9,0))) -> 974.22
A10: 45292 | B10: overhead | C10: NA | D10: NA | E10: 2000 | F10: =IFERROR(LEFT(B10,FIND(":",B10)-1),B10) -> overhead | G10: NA | H10: =YEAR(A10) -> 2024 | I10: =MONTH(A10) -> 1 | J10: =IF(F10="net sales",E10, IF(F10="cogs",-E10, IF(OR(F10="marketing",F10="overhead",F10="payroll",F10="interest","amortization"),-E10,0))) -> -2000
A11: 45293 | B11: cogs:product 1 | C11: 5.99 | D11: 65 | E11: 389.35 | F11: =IFERROR(LEFT(B11,FIND(":",B11)-1),B11) -> cogs | G11: =IFERROR(RIGHT(B11,LEN(B11)-FIND(":",B11)),"") -> product 1 | H11: =YEAR(A11) -> 2024 | I11: =MONTH(A11) -> 1 | J11: =IF(F11="net sales",E11, IF(F11="cogs",-E11, IF(OR(F11="marketing",F11="overhead",F11="payroll",F11="interest","amortization"),-E11,0))) -> -389.35
A12: 45293 | B12: cogs:product 2 | C12: 16.99 | D12: 3 | E12: 50.97 | F12: =IFERROR(LEFT(B12,FIND(":",B12)-1),B12) -> cogs | G12: =IFERROR(RIGHT(B12,LEN(B12)-FIND(":",B12)),"") -> product 2 | H12: =YEAR(A12) -> 2024 | I12: =MONTH(A12) -> 1 | J12: =IF(F12="net sales",E12, IF(F12="cogs",-E12, IF(OR(F12="marketing",F12="overhead",F12="payroll",F12="interest","amortization"),-E12,0))) -> -50.97
A13: 45293 | B13: cogs:product 3 | C13: 8.49 | D13: 226 | E13: 1918.74 | F13: =IFERROR(LEFT(B13,FIND(":",B13)-1),B13) -> cogs | G13: =IFERROR(RIGHT(B13,LEN(B13)-FIND(":",B13)),"") -> product 3 | H13: =YEAR(A13) -> 2024 | I13: =MONTH(A13) -> 1 | J13: =IF(F13="net sales",E13, IF(F13="cogs",-E13, IF(OR(F13="marketing",F13="overhead",F13="payroll",F13="interest","amortization"),-E13,0))) -> -1918.74
A14: 45293 | B14: marketing | C14: NA | D14: NA | E14: 99.96 | F14: =IFERROR(LEFT(B14,FIND(":",B14)-1),B14) -> marketing | G14: NA | H14: =YEAR(A14) -> 2024 | I14: =MONTH(A14) -> 1 | J14: =IF(F14="net sales",E14, IF(F14="cogs",-E14, IF(OR(F14="marketing",F14="overhead",F14="payroll",F14="interest","amortization"),-E14,0))) -> -99.96
A15: 45293 | B15: net sales:product 1 | C15: 9.99 | D15: 65 | E15: 649.35 | F15: =IFERROR(LEFT(B15,FIND(":",B15)-1),B15) -> net sales | G15: =IFERROR(RIGHT(B15,LEN(B15)-FIND(":",B15)),"") -> product 1 | H15: =YEAR(A15) -> 2024 | I15: =MONTH(A15) -> 1 | J15: =IF(F15="net sales",E15, IF(F15="cogs",-E15, IF(OR(F15="marketing",F15="overhead",F15="payroll",F15="interest","amortization"),-E15,0))) -> 649.35
A16: 45293 | B16: net sales:product 2 | C16: 24.99 | D16: 3 | E16: 74.97 | F16: =IFERROR(LEFT(B16,FIND(":",B16)-1),B16) -> net sales | G16: =IFERROR(RIGHT(B16,LEN(B16)-FIND(":",B16)),"") -> product 2 | H16: =YEAR(A16) -> 2024 | I16: =MONTH(A16) -> 1 | J16: =IF(F16="net sales",E16, IF(F16="cogs",-E16, IF(OR(F16="marketing",F16="overhead",F16="payroll",F16="interest","amortization"),-E16,0))) -> 74.97
A17: 45293 | B17: net sales:product 3 | C17: 12.49 | D17: 226 | E17: 2822.74 | F17: =IFERROR(LEFT(B17,FIND(":",B17)-1),B17) -> net sales | G17: =IFERROR(RIGHT(B17,LEN(B17)-FIND(":",B17)),"") -> product 3 | H17: =YEAR(A17) -> 2024 | I17: =MONTH(A17) -> 1 | J17: =IF(F17="net sales",E17, IF(F17="cogs",-E17, IF(OR(F17="marketing",F17="overhead",F17="payroll",F17="interest","amortization"),-E17,0))) -> 2822.74
A18: 45294 | B18: cogs:product 1 | C18: 5.99 | D18: 37 | E18: 221.63 | F18: =IFERROR(LEFT(B18,FIND(":",B18)-1),B18) -> cogs | G18: =IFERROR(RIGHT(B18,LEN(B18)-FIND(":",B18)),"") -> product 1 | H18: =YEAR(A18) -> 2024 | I18: =MONTH(A18) -> 1 | J18: =IF(F18="net sales",E18, IF(F18="cogs",-E18, IF(OR(F18="marketing",F18="overhead",F18="payroll",F18="interest","amortization"),-E18,0))) -> -221.63
A19: 45294 | B19: cogs:product 2 | C19: 16.99 | D19: 9 | E19: 152.91 | F19: =IFERROR(LEFT(B19,FIND(":",B19)-1),B19) -> cogs | G19: =IFERROR(RIGHT(B19,LEN(B19)-FIND(":",B19)),"") -> product 2 | H19: =YEAR(A19) -> 2024 | I19: =MONTH(A19) -> 1 | J19: =IF(F19="net sales",E19, IF(F19="cogs",-E19, IF(OR(F19="marketing",F19="overhead",F19="payroll",F19="interest","amortization"),-E19,0))) -> -152.91
A20: 45294 | B20: cogs:product 3 | C20: 8.49 | D20: 222 | E20: 1884.78 | F20: =IFERROR(LEFT(B20,FIND(":",B20)-1),B20) -> cogs | G20: =IFERROR(RIGHT(B20,LEN(B20)-FIND(":",B20)),"") -> product 3 | H20: =YEAR(A20) -> 2024 | I20: =MONTH(A20) -> 1 | J20: =IF(F20="net sales",E20, IF(F20="cogs",-E20, IF(OR(F20="marketing",F20="overhead",F20="payroll",F20="interest","amortization"),-E20,0))) -> -1884.78
A21: 45294 | B21: marketing | C21: NA | D21: NA | E21: 99.91 | F21: =IFERROR(LEFT(B21,FIND(":",B21)-1),B21) -> marketing | G21: NA | H21: =YEAR(A21) -> 2024 | I21: =MONTH(A21) -> 1 | J21: =IF(F21="net sales",E21, IF(F21="cogs",-E21, IF(OR(F21="marketing",F21="overhead",F21="payroll",F21="interest","amortization"),-E21,0))) -> -99.91
A22: 45294 | B22: net sales:product 1 | C22: 9.99 | D22: 37 | E22: 369.63 | F22: =IFERROR(LEFT(B22,FIND(":",B22)-1),B22) -> net sales | G22: =IFERROR(RIGHT(B22,LEN(B22)-FIND(":",B22)),"") -> product 1 | H22: =YEAR(A22) -> 2024 | I22: =MONTH(A22) -> 1 | J22: =IF(F22="net sales",E22, IF(F22="cogs",-E22, IF(OR(F22="marketing",F22="overhead",F22="payroll",F22="interest","amortization"),-E22,0))) -> 369.63
A23: 45294 | B23: net sales:product 2 | C23: 24.99 | D23: 9 | E23: 224.91 | F23: =IFERROR(LEFT(B23,FIND(":",B23)-1),B23) -> net sales | G23: =IFERROR(RIGHT(B23,LEN(B23)-FIND(":",B23)),"") -> product 2 | H23: =YEAR(A23) -> 2024 | I23: =MONTH(A23) -> 1 | J23: =IF(F23="net sales",E23, IF(F23="cogs",-E23, IF(OR(F23="marketing",F23="overhead",F23="payroll",F23="interest","amortization"),-E23,0))) -> 224.91
A24: 45294 | B24: net sales:product 3 | C24: 12.49 | D24: 222 | E24: 2772.78 | F24: =IFERROR(LEFT(B24,FIND(":",B24)-1),B24) -> net sales | G24: =IFERROR(RIGHT(B24,LEN(B24)-FIND(":",B24)),"") -> product 3 | H24: =YEAR(A24) -> 2024 | I24: =MONTH(A24) -> 1 | J24: =IF(F24="net sales",E24, IF(F24="cogs",-E24, IF(OR(F24="marketing",F24="overhead",F24="payroll",F24="interest","amortization"),-E24,0))) -> 2772.78
A25: 45295 | B25: cogs:product 1 | C25: 5.99 | D25: 39 | E25: 233.61 | F25: =IFERROR(LEFT(B25,FIND(":",B25)-1),B25) -> cogs | G25: =IFERROR(RIGHT(B25,LEN(B25)-FIND(":",B25)),"") -> product 1 | H25: =YEAR(A25) -> 2024 | I25: =MONTH(A25) -> 1 | J25: =IF(F25="net sales",E25, IF(F25="cogs",-E25, IF(OR(F25="marketing",F25="overhead",F25="payroll",F25="interest","amortization"),-E25,0))) -> -233.61
A26: 45295 | B26: cogs:product 2 | C26: 16.99 | D26: 2 | E26: 33.98 | F26: =IFERROR(LEFT(B26,FIND(":",B26)-1),B26) -> cogs | G26: =IFERROR(RIGHT(B26,LEN(B26)-FIND(":",B26)),"") -> product 2 | H26: =YEAR(A26) -> 2024 | I26: =MONTH(A26) -> 1 | J26: =IF(F26="net sales",E26, IF(F26="cogs",-E26, IF(OR(F26="marketing",F26="overhead",F26="payroll",F26="interest","amortization"),-E26,0))) -> -33.98
A27: 45295 | B27: cogs:product 3 | C27: 8.49 | D27: 180 | E27: 1528.2 | F27: =IFERROR(LEFT(B27,FIND(":",B27)-1),B27) -> cogs | G27: =IFERROR(RIGHT(B27,LEN(B27)-FIND(":",B27)),"") -> product 3 | H27: =YEAR(A27) -> 2024 | I27: =MONTH(A27) -> 1 | J27: =IF(F27="net sales",E27, IF(F27="cogs",-E27, IF(OR(F27="marketing",F27="overhead",F27="payroll",F27="interest","amortization"),-E27,0))) -> -1528.2
A28: 45295 | B28: marketing | C28: NA | D28: NA | E28: 99.98 | F28: =IFERROR(LEFT(B28,FIND(":",B28)-1),B28) -> marketing | G28: NA | H28: =YEAR(A28) -> 2024 | I28: =MONTH(A28) -> 1 | J28: =IF(F28="net sales",E28, IF(F28="cogs",-E28, IF(OR(F28="marketing",F28="overhead",F28="payroll",F28="interest","amortization"),-E28,0))) -> -99.98
A29: 45295 | B29: net sales:product 1 | C29: 9.99 | D29: 39 | E29: 389.61 | F29: =IFERROR(LEFT(B29,FIND(":",B29)-1),B29) -> net sales | G29: =IFERROR(RIGHT(B29,LEN(B29)-FIND(":",B29)),"") -> product 1 | H29: =YEAR(A29) -> 2024 | I29: =MONTH(A29) -> 1 | J29: =IF(F29="net sales",E29, IF(F29="cogs",-E29, IF(OR(F29="marketing",F29="overhead",F29="payroll",F29="interest","amortization"),-E29,0))) -> 389.61
A30: 45295 | B30: net sales:product 2 | C30: 24.99 | D30: 2 | E30: 49.98 | F30: =IFERROR(LEFT(B30,FIND(":",B30)-1),B30) -> net sales | G30: =IFERROR(RIGHT(B30,LEN(B30)-FIND(":",B30)),"") -> product 2 | H30: =YEAR(A30) -> 2024 | I30: =MONTH(A30) -> 1 | J30: =IF(F30="net sales",E30, IF(F30="cogs",-E30, IF(OR(F30="marketing",F30="overhead",F30="payroll",F30="interest","amortization"),-E30,0))) -> 49.98
A31: 45295 | B31: net sales:product 3 | C31: 12.49 | D31: 180 | E31: 2248.2 | F31: =IFERROR(LEFT(B31,FIND(":",B31)-1),B31) -> net sales | G31: =IFERROR(RIGHT(B31,LEN(B31)-FIND(":",B31)),"") -> product 3 | H31: =YEAR(A31) -> 2024 | I31: =MONTH(A31) -> 1 | J31: =IF(F31="net sales",E31, IF(F31="cogs",-E31, IF(OR(F31="marketing",F31="overhead",F31="payroll",F31="interest","amortization"),-E31,0))) -> 2248.2
A32: 45296 | B32: cogs:product 1 | C32: 5.99 | D32: 73 | E32: 437.27 | F32: =IFERROR(LEFT(B32,FIND(":",B32)-1),B32) -> cogs | G32: =IFERROR(RIGHT(B32,LEN(B32)-FIND(":",B32)),"") -> product 1 | H32: =YEAR(A32) -> 2024 | I32: =MONTH(A32) -> 1 | J32: =IF(F32="net sales",E32, IF(F32="cogs",-E32, IF(OR(F32="marketing",F32="overhead",F32="payroll",F32="interest","amortization"),-E32,0))) -> -437.27
A33: 45296 | B33: cogs:product 2 | C33: 16.99 | D33: 7 | E33: 118.93 | F33: =IFERROR(LEFT(B33,FIND(":",B33)-1),B33) -> cogs | G33: =IFERROR(RIGHT(B33,LEN(B33)-FIND(":",B33)),"") -> product 2 | H33: =YEAR(A33) -> 2024 | I33: =MONTH(A33) -> 1 | J33: =IF(F33="net sales",E33, IF(F33="cogs",-E33, IF(OR(F33="marketing",F33="overhead",F33="payroll",F33="interest","amortization"),-E33,0))) -> -118.93
A34: 45296 | B34: cogs:product 3 | C34: 8.49 | D34: 95 | E34: 806.55 | F34: =IFERROR(LEFT(B34,FIND(":",B34)-1),B34) -> cogs | G34: =IFERROR(RIGHT(B34,LEN(B34)-FIND(":",B34)),"") -> product 3 | H34: =YEAR(A34) -> 2024 | I34: =MONTH(A34) -> 1 | J34: =IF(F34="net sales",E34, IF(F34="cogs",-E34, IF(OR(F34="marketing",F34="overhead",F34="payroll",F34="interest","amortization"),-E34,0))) -> -806.55
A35: 45296 | B35: marketing | C35: NA | D35: NA | E35: 100.03 | F35: =IFERROR(LEFT(B35,FIND(":",B35)-1),B35) -> marketing | G35: NA | H35: =YEAR(A35) -> 2024 | I35: =MONTH(A35) -> 1 | J35: =IF(F35="net sales",E35, IF(F35="cogs",-E35, IF(OR(F35="marketing",F35="overhead",F35="payroll",F35="interest","amortization"),-E35,0))) -> -100.03
A36: 45296 | B36: net sales:product 1 | C36: 9.99 | D36: 73 | E36: 729.27 | F36: =IFERROR(LEFT(B36,FIND(":",B36)-1),B36) -> net sales | G36: =IFERROR(RIGHT(B36,LEN(B36)-FIND(":",B36)),"") -> product 1 | H36: =YEAR(A36) -> 2024 | I36: =MONTH(A36) -> 1 | J36: =IF(F36="net sales",E36, IF(F36="cogs",-E36, IF(OR(F36="marketing",F36="overhead",F36="payroll",F36="interest","amortization"),-E36,0))) -> 729.27
A37: 45296 | B37: net sales:product 2 | C37: 24.99 | D37: 7 | E37: 174.93 | F37: =IFERROR(LEFT(B37,FIND(":",B37)-1),B37) -> net sales | G37: =IFERROR(RIGHT(B37,LEN(B37)-FIND(":",B37)),"") -> product 2 | H37: =YEAR(A37) -> 2024 | I37: =MONTH(A37) -> 1 | J37: =IF(F37="net sales",E37, IF(F37="cogs",-E37, IF(OR(F37="marketing",F37="overhead",F37="payroll",F37="interest","amortization"),-E37,0))) -> 174.93
A38: 45296 | B38: net sales:product 3 | C38: 12.49 | D38: 95 | E38: 1186.55 | F38: =IFERROR(LEFT(B38,FIND(":",B38)-1),B38) -> net sales | G38: =IFERROR(RIGHT(B38,LEN(B38)-FIND(":",B38)),"") -> product 3 | H38: =YEAR(A38) -> 2024 | I38: =MONTH(A38) -> 1 | J38: =IF(F38="net sales",E38, IF(F38="cogs",-E38, IF(OR(F38="marketing",F38="overhead",F38="payroll",F38="interest","amortization"),-E38,0))) -> 1186.55
A39: 45296 | B39: payroll | C39: NA | D39: NA | E39: 1200 | F39: =IFERROR(LEFT(B39,FIND(":",B39)-1),B39) -> payroll | G39: NA | H39: =YEAR(A39) -> 2024 | I39: =MONTH(A39) -> 1 | J39: =IF(F39="net sales",E39, IF(F39="cogs",-E39, IF(OR(F39="marketing",F39="overhead",F39="payroll",F39="interest","amortization"),-E39,0))) -> -1200
A40: 45297 | B40: cogs:product 1 | C40: 5.99 | D40: 38 | E40: 227.62 | F40: =IFERROR(LEFT(B40,FIND(":",B40)-1),B40) -> cogs | G40: =IFERROR(RIGHT(B40,LEN(B40)-FIND(":",B40)),"") -> product 1 | H40: =YEAR(A40) -> 2024 | I40: =MONTH(A40) -> 1 | J40: =IF(F40="net sales",E40, IF(F40="cogs",-E40, IF(OR(F40="marketing",F40="overhead",F40="payroll",F40="interest","amortization"),-E40,0))) -> -227.62
A41: 45297 | B41: cogs:product 2 | C41: 16.99 | D41: 8 | E41: 135.92 | F41: =IFERROR(LEFT(B41,FIND(":",B41)-1),B41) -> cogs | G41: =IFERROR(RIGHT(B41,LEN(B41)-FIND(":",B41)),"") -> product 2 | H41: =YEAR(A41) -> 2024 | I41: =MONTH(A41) -> 1 | J41: =IF(F41="net sales",E41, IF(F41="cogs",-E41, IF(OR(F41="marketing",F41="overhead",F41="payroll",F41="interest","amortization"),-E41,0))) -> -135.92
A42: 45297 | B42: cogs:product 3 | C42: 8.49 | D42: 103 | E42: 874.47 | F42: =IFERROR(LEFT(B42,FIND(":",B42)-1),B42) -> cogs | G42: =IFERROR(RIGHT(B42,LEN(B42)-FIND(":",B42)),"") -> product 3 | H42: =YEAR(A42) -> 2024 | I42: =MONTH(A42) -> 1 | J42: =IF(F42="net sales",E42, IF(F42="cogs",-E42, IF(OR(F42="marketing",F42="overhead",F42="payroll",F42="interest","amortization"),-E42,0))) -> -874.47
A43: 45297 | B43: marketing | C43: NA | D43: NA | E43: 100.08 | F43: =IFERROR(LEFT(B43,FIND(":",B43)-1),B43) -> marketing | G43: NA | H43: =YEAR(A43) -> 2024 | I43: =MONTH(A43) -> 1 | J43: =IF(F43="net sales",E43, IF(F43="cogs",-E43, IF(OR(F43="marketing",F43="overhead",F43="payroll",F43="interest","amortization"),-E43,0))) -> -100.08
A44: 45297 | B44: net sales:product 1 | C44: 9.99 | D44: 38 | E44: 379.62 | F44: =IFERROR(LEFT(B44,FIND(":",B44)-1),B44) -> net sales | G44: =IFERROR(RIGHT(B44,LEN(B44)-FIND(":",B44)),"") -> product 1 | H44: =YEAR(A44) -> 2024 | I44: =MONTH(A44) -> 1 | J44: =IF(F44="net sales",E44, IF(F44="cogs",-E44, IF(OR(F44="marketing",F44="overhead",F44="payroll",F44="interest","amortization"),-E44,0))) -> 379.62
A45: 45297 | B45: net sales:product 2 | C45: 24.99 | D45: 8 | E45: 199.92 | F45: =IFERROR(LEFT(B45,FIND(":",B45)-1),B45) -> net sales | G45: =IFERROR(RIGHT(B45,LEN(B45)-FIND(":",B45)),"") -> product 2 | H45: =YEAR(A45) -> 2024 | I45: =MONTH(A45) -> 1 | J45: =IF(F45="net sales",E45, IF(F45="cogs",-E45, IF(OR(F45="marketing",F45="overhead",F45="payroll",F45="interest","amortization"),-E45,0))) -> 199.92
A46: 45297 | B46: net sales:product 3 | C46: 12.49 | D46: 103 | E46: 1286.47 | F46: =IFERROR(LEFT(B46,FIND(":",B46)-1),B46) -> net sales | G46: =IFERROR(RIGHT(B46,LEN(B46)-FIND(":",B46)),"") -> product 3 | H46: =YEAR(A46) -> 2024 | I46: =MONTH(A46) -> 1 | J46: =IF(F46="net sales",E46, IF(F46="cogs",-E46, IF(OR(F46="marketing",F46="overhead",F46="payroll",F46="interest","amortization"),-E46,0))) -> 1286.47
A47: 45298 | B47: cogs:product 1 | C47: 5.99 | D47: 85 | E47: 509.15 | F47: =IFERROR(LEFT(B47,FIND(":",B47)-1),B47) -> cogs | G47: =IFERROR(RIGHT(B47,LEN(B47)-FIND(":",B47)),"") -> product 1 | H47: =YEAR(A47) -> 2024 | I47: =MONTH(A47) -> 1 | J47: =IF(F47="net sales",E47, IF(F47="cogs",-E47, IF(OR(F47="marketing",F47="overhead",F47="payroll",F47="interest","amortization"),-E47,0))) -> -509.15
A48: 45298 | B48: cogs:product 2 | C48: 16.99 | D48: 4 | E48: 67.96 | F48: =IFERROR(LEFT(B48,FIND(":",B48)-1),B48) -> cogs | G48: =IFERROR(RIGHT(B48,LEN(B48)-FIND(":",B48)),"") -> product 2 | H48: =YEAR(A48) -> 2024 | I48: =MONTH(A48) -> 1 | J48: =IF(F48="net sales",E48, IF(F48="cogs",-E48, IF(OR(F48="marketing",F48="overhead",F48="payroll",F48="interest","amortization"),-E48,0))) -> -67.96
A49: 45298 | B49: cogs:product 3 | C49: 8.49 | D49: 73 | E49: 619.77 | F49: =IFERROR(LEFT(B49,FIND(":",B49)-1),B49) -> cogs | G49: =IFERROR(RIGHT(B49,LEN(B49)-FIND(":",B49)),"") -> product 3 | H49: =YEAR(A49) -> 2024 | I49: =MONTH(A49) -> 1 | J49: =IF(F49="net sales",E49, IF(F49="cogs",-E49, IF(OR(F49="marketing",F49="overhead",F49="payroll",F49="interest","amortization"),-E49,0))) -> -619.77
A50: 45298 | B50: marketing | C50: NA | D50: NA | E50: 100.01 | F50: =IFERROR(LEFT(B50,FIND(":",B50)-1),B50) -> marketing | G50: NA | H50: =YEAR(A50) -> 2024 | I50: =MONTH(A50) -> 1 | J50: =IF(F50="net sales",E50, IF(F50="cogs",-E50, IF(OR(F50="marketing",F50="overhead",F50="payroll",F50="interest","amortization"),-E50,0))) -> -100.01
A51: 45298 | B51: net sales:product 1 | C51: 9.99 | D51: 85 | E51: 849.15 | F51: =IFERROR(LEFT(B51,FIND(":",B51)-1),B51) -> net sales | G51: =IFERROR(RIGHT(B51,LEN(B51)-FIND(":",B51)),"") -> product 1 | H51: =YEAR(A51) -> 2024 | I51: =MONTH(A51) -> 1 | J51: =IF(F51="net sales",E51, IF(F51="cogs",-E51, IF(OR(F51="marketing",F51="overhead",F51="payroll",F51="interest","amortization"),-E51,0))) -> 849.15
A52: 45298 | B52: net sales:product 2 | C52: 24.99 | D52: 4 | E52: 99.96 | F52: =IFERROR(LEFT(B52,FIND(":",B52)-1),B52) -> net sales | G52: =IFERROR(RIGHT(B52,LEN(B52)-FIND(":",B52)),"") -> product 2 | H52: =YEAR(A52) -> 2024 | I52: =MONTH(A52) -> 1 | J52: =IF(F52="net sales",E52, IF(F52="cogs",-E52, IF(OR(F52="marketing",F52="overhead",F52="payroll",F52="interest","amortization"),-E52,0))) -> 99.96
A53: 45298 | B53: net sales:product 3 | C53: 12.49 | D53: 73 | E53: 911.77 | F53: =IFERROR(LEFT(B53,FIND(":",B53)-1),B53) -> net sales | G53: =IFERROR(RIGHT(B53,LEN(B53)-FIND(":",B53)),"") -> product 3 | H53: =YEAR(A53) -> 2024 | I53: =MONTH(A53) -> 1 | J53: =IF(F53="net sales",E53, IF(F53="cogs",-E53, IF(OR(F53="marketing",F53="overhead",F53="payroll",F53="interest","amortization"),-E53,0))) -> 911.77
A54: 45299 | B54: cogs:product 1 | C54: 5.99 | D54: 9 | E54: 53.91 | F54: =IFERROR(LEFT(B54,FIND(":",B54)-1),B54) -> cogs | G54: =IFERROR(RIGHT(B54,LEN(B54)-FIND(":",B54)),"") -> product 1 | H54: =YEAR(A54) -> 2024 | I54: =MONTH(A54) -> 1 | J54: =IF(F54="net sales",E54, IF(F54="cogs",-E54, IF(OR(F54="marketing",F54="overhead",F54="payroll",F54="interest","amortization"),-E54,0))) -> -53.91
A55: 45299 | B55: cogs:product 2 | C55: 16.99 | D55: 7 | E55: 118.93 | F55: =IFERROR(LEFT(B55,FIND(":",B55)-1),B55) -> cogs | G55: =IFERROR(RIGHT(B55,LEN(B55)-FIND(":",B55)),"") -> product 2 | H55: =YEAR(A55) -> 2024 | I55: =MONTH(A55) -> 1 | J55: =IF(F55="net sales",E55, IF(F55="cogs",-E55, IF(OR(F55="marketing",F55="overhead",F55="payroll",F55="interest","amortization"),-E55,0))) -> -118.93
A56: 45299 | B56: cogs:product 3 | C56: 8.49 | D56: 249 | E56: 2114.01 | F56: =IFERROR(LEFT(B56,FIND(":",B56)-1),B56) -> cogs | G56: =IFERROR(RIGHT(B56,LEN(B56)-FIND(":",B56)),"") -> product 3 | H56: =YEAR(A56) -> 2024 | I56: =MONTH(A56) -> 1 | J56: =IF(F56="net sales",E56, IF(F56="cogs",-E56, IF(OR(F56="marketing",F56="overhead",F56="payroll",F56="interest","amortization"),-E56,0))) -> -2114.01
A57: 45299 | B57: marketing | C57: NA | D57: NA | E57: 99.92 | F57: =IFERROR(LEFT(B57,FIND(":",B57)-1),B57) -> marketing | G57: NA | H57: =YEAR(A57) -> 2024 | I57: =MONTH(A57) -> 1 | J57: =IF(F57="net sales",E57, IF(F57="cogs",-E57, IF(OR(F57="marketing",F57="overhead",F57="payroll",F57="interest","amortization"),-E57,0))) -> -99.92
A58: 45299 | B58: net sales:product 1 | C58: 9.99 | D58: 9 | E58: 89.91 | F58: =IFERROR(LEFT(B58,FIND(":",B58)-1),B58) -> net sales | G58: =IFERROR(RIGHT(B58,LEN(B58)-FIND(":",B58)),"") -> product 1 | H58: =YEAR(A58) -> 2024 | I58: =MONTH(A58) -> 1 | J58: =IF(F58="net sales",E58, IF(F58="cogs",-E58, IF(OR(F58="marketing",F58="overhead",F58="payroll",F58="interest","amortization"),-E58,0))) -> 89.91
A59: 45299 | B59: net sales:product 2 | C59: 24.99 | D59: 7 | E59: 174.93 | F59: =IFERROR(LEFT(B59,FIND(":",B59)-1),B59) -> net sales | G59: =IFERROR(RIGHT(B59,LEN(B59)-FIND(":",B59)),"") -> product 2 | H59: =YEAR(A59) -> 2024 | I59: =MONTH(A59) -> 1 | J59: =IF(F59="net sales",E59, IF(F59="cogs",-E59, IF(OR(F59="marketing",F59="overhead",F59="payroll",F59="interest","amortization"),-E59,0))) -> 174.93
A60: 45299 | B60: net sales:product 3 | C60: 12.49 | D60: 249 | E60: 3110.01 | F60: =IFERROR(LEFT(B60,FIND(":",B60)-1),B60) -> net sales | G60: =IFERROR(RIGHT(B60,LEN(B60)-FIND(":",B60)),"") -> product 3 | H60: =YEAR(A60) -> 2024 | I60: =MONTH(A60) -> 1 | J60: =IF(F60="net sales",E60, IF(F60="cogs",-E60, IF(OR(F60="marketing",F60="overhead",F60="payroll",F60="interest","amortization"),-E60,0))) -> 3110.01
A61: 45300 | B61: cogs:product 1 | C61: 5.99 | D61: 12 | E61: 71.88 | F61: =IFERROR(LEFT(B61,FIND(":",B61)-1),B61) -> cogs | G61: =IFERROR(RIGHT(B61,LEN(B61)-FIND(":",B61)),"") -> product 1 | H61: =YEAR(A61) -> 2024 | I61: =MONTH(A61) -> 1 | J61: =IF(F61="net sales",E61, IF(F61="cogs",-E61, IF(OR(F61="marketing",F61="overhead",F61="payroll",F61="interest","amortization"),-E61,0))) -> -71.88
A62: 45300 | B62: cogs:product 2 | C62: 16.99 | D62: 10 | E62: 169.9 | F62: =IFERROR(LEFT(B62,FIND(":",B62)-1),B62) -> cogs | G62: =IFERROR(RIGHT(B62,LEN(B62)-FIND(":",B62)),"") -> product 2 | H62: =YEAR(A62) -> 2024 | I62: =MONTH(A62) -> 1 | J62: =IF(F62="net sales",E62, IF(F62="cogs",-E62, IF(OR(F62="marketing",F62="overhead",F62="payroll",F62="interest","amortization"),-E62,0))) -> -169.9
A63: 45300 | B63: cogs:product 3 | C63: 8.49 | D63: 0 | E63: =C63*D63 -> 0 | F63: =IFERROR(LEFT(B63,FIND(":",B63)-1),B63) -> cogs | G63: =IFERROR(RIGHT(B63,LEN(B63)-FIND(":",B63)),"") -> product 3 | H63: =YEAR(A63) -> 2024 | I63: =MONTH(A63) -> 1 | J63: =IF(F63="net sales",E63, IF(F63="cogs",-E63, IF(OR(F63="marketing",F63="overhead",F63="payroll",F63="interest","amortization"),-E63,0))) -> 0
A64: 45300 | B64: marketing | C64: NA | D64: NA | E64: 99.92 | F64: =IFERROR(LEFT(B64,FIND(":",B64)-1),B64) -> marketing | G64: NA | H64: =YEAR(A64) -> 2024 | I64: =MONTH(A64) -> 1 | J64: =IF(F64="net sales",E64, IF(F64="cogs",-E64, IF(OR(F64="marketing",F64="overhead",F64="payroll",F64="interest","amortization"),-E64,0))) -> -99.92
A65: 45300 | B65: net sales:product 1 | C65: 9.99 | D65: 12 | E65: 119.88 | F65: =IFERROR(LEFT(B65,FIND(":",B65)-1),B65) -> net sales | G65: =IFERROR(RIGHT(B65,LEN(B65)-FIND(":",B65)),"") -> product 1 | H65: =YEAR(A65) -> 2024 | I65: =MONTH(A65) -> 1 | J65: =IF(F65="net sales",E65, IF(F65="cogs",-E65, IF(OR(F65="marketing",F65="overhead",F65="payroll",F65="interest","amortization"),-E65,0))) -> 119.88
A66: 45300 | B66: net sales:product 2 | C66: 24.99 | D66: 10 | E66: 249.9 | F66: =IFERROR(LEFT(B66,FIND(":",B66)-1),B66) -> net sales | G66: =IFERROR(RIGHT(B66,LEN(B66)-FIND(":",B66)),"") -> product 2 | H66: =YEAR(A66) -> 2024 | I66: =MONTH(A66) -> 1 | J66: =IF(F66="net sales",E66, IF(F66="cogs",-E66, IF(OR(F66="marketing",F66="overhead",F66="payroll",F66="interest","amortization"),-E66,0))) -> 249.9
A67: 45300 | B67: net sales:product 3 | C67: 12.49 | D67: 0 | E67: =C67*D67 -> 0 | F67: =IFERROR(LEFT(B67,FIND(":",B67)-1),B67) -> net sales | G67: =IFERROR(RIGHT(B67,LEN(B67)-FIND(":",B67)),"") -> product 3 | H67: =YEAR(A67) -> 2024 | I67: =MONTH(A67) -> 1 | J67: =IF(F67="net sales",E67, IF(F67="cogs",-E67, IF(OR(F67="marketing",F67="overhead",F67="payroll",F67="interest","amortization"),-E67,0))) -> 0
A68: 45301 | B68: cogs:product 1 | C68: 5.99 | D68: 99 | E68: 593.01 | F68: =IFERROR(LEFT(B68,FIND(":",B68)-1),B68) -> cogs | G68: =IFERROR(RIGHT(B68,LEN(B68)-FIND(":",B68)),"") -> product 1 | H68: =YEAR(A68) -> 2024 | I68: =MONTH(A68) -> 1 | J68: =IF(F68="net sales",E68, IF(F68="cogs",-E68, IF(OR(F68="marketing",F68="overhead",F68="payroll",F68="interest","amortization"),-E68,0))) -> -593.01
A69: 45301 | B69: cogs:product 2 | C69: 16.99 | D69: 1 | E69: 16.99 | F69: =IFERROR(LEFT(B69,FIND(":",B69)-1),B69) -> cogs | G69: =IFERROR(RIGHT(B69,LEN(B69)-FIND(":",B69)),"") -> product 2 | H69: =YEAR(A69) -> 2024 | I69: =MONTH(A69) -> 1 | J69: =IF(F69="net sales",E69, IF(F69="cogs",-E69, IF(OR(F69="marketing",F69="overhead",F69="payroll",F69="interest","amortization"),-E69,0))) -> -16.99
A70: 45301 | B70: cogs:product 3 | C70: 8.49 | D70: 21 | E70: 178.29 | F70: =IFERROR(LEFT(B70,FIND(":",B70)-1),B70) -> cogs | G70: =IFERROR(RIGHT(B70,LEN(B70)-FIND(":",B70)),"") -> product 3 | H70: =YEAR(A70) -> 2024 | I70: =MONTH(A70) -> 1 | J70: =IF(F70="net sales",E70, IF(F70="cogs",-E70, IF(OR(F70="marketing",F70="overhead",F70="payroll",F70="interest","amortization"),-E70,0))) -> -178.29
A71: 45301 | B71: marketing | C71: NA | D71: NA | E71: 100.05 | F71: =IFERROR(LEFT(B71,FIND(":",B71)-1),B71) -> marketing | G71: NA | H71: =YEAR(A71) -> 2024 | I71: =MONTH(A71) -> 1 | J71: =IF(F71="net sales",E71, IF(F71="cogs",-E71, IF(OR(F71="marketing",F71="overhead",F71="payroll",F71="interest","amortization"),-E71,0))) -> -100.05
A72: 45301 | B72: net sales:product 1 | C72: 9.99 | D72: 99 | E72: 989.01 | F72: =IFERROR(LEFT(B72,FIND(":",B72)-1),B72) -> net sales | G72: =IFERROR(RIGHT(B72,LEN(B72)-FIND(":",B72)),"") -> product 1 | H72: =YEAR(A72) -> 2024 | I72: =MONTH(A72) -> 1 | J72: =IF(F72="net sales",E72, IF(F72="cogs",-E72, IF(OR(F72="marketing",F72="overhead",F72="payroll",F72="interest","amortization"),-E72,0))) -> 989.01
A73: 45301 | B73: net sales:product 2 | C73: 24.99 | D73: 1 | E73: 24.99 | F73: =IFERROR(LEFT(B73,FIND(":",B73)-1),B73) -> net sales | G73: =IFERROR(RIGHT(B73,LEN(B73)-FIND(":",B73)),"") -> product 2 | H73: =YEAR(A73) -> 2024 | I73: =MONTH(A73) -> 1 | J73: =IF(F73="net sales",E73, IF(F73="cogs",-E73, IF(OR(F73="marketing",F73="overhead",F73="payroll",F73="interest","amortization"),-E73,0))) -> 24.99
A74: 45301 | B74: net sales:product 3 | C74: 12.49 | D74: 21 | E74: 262.29 | F74: =IFERROR(LEFT(B74,FIND(":",B74)-1),B74) -> net sales | G74: =IFERROR(RIGHT(B74,LEN(B74)-FIND(":",B74)),"") -> product 3 | H74: =YEAR(A74) -> 2024 | I74: =MONTH(A74) -> 1 | J74: =IF(F74="net sales",E74, IF(F74="cogs",-E74, IF(OR(F74="marketing",F74="overhead",F74="payroll",F74="interest","amortization"),-E74,0))) -> 262.29
A75: 45302 | B75: cogs:product 1 | C75: 5.99 | D75: 21 | E75: 125.79 | F75: =IFERROR(LEFT(B75,FIND(":",B75)-1),B75) -> cogs | G75: =IFERROR(RIGHT(B75,LEN(B75)-FIND(":",B75)),"") -> product 1 | H75: =YEAR(A75) -> 2024 | I75: =MONTH(A75) -> 1 | J75: =IF(F75="net sales",E75, IF(F75="cogs",-E75, IF(OR(F75="marketing",F75="overhead",F75="payroll",F75="interest","amortization"),-E75,0))) -> -125.79
A76: 45302 | B76: cogs:product 2 | C76: 16.99 | D76: 2 | E76: 33.98 | F76: =IFERROR(LEFT(B76,FIND(":",B76)-1),B76) -> cogs | G76: =IFERROR(RIGHT(B76,LEN(B76)-FIND(":",B76)),"") -> product 2 | H76: =YEAR(A76) -> 2024 | I76: =MONTH(A76) -> 1 | J76: =IF(F76="net sales",E76, IF(F76="cogs",-E76, IF(OR(F76="marketing",F76="overhead",F76="payroll",F76="interest","amortization"),-E76,0))) -> -33.98
A77: 45302 | B77: cogs:product 3 | C77: 8.49 | D77: 157 | E77: 1332.93 | F77: =IFERROR(LEFT(B77,FIND(":",B77)-1),B77) -> cogs | G77: =IFERROR(RIGHT(B77,LEN(B77)-FIND(":",B77)),"") -> product 3 | H77: =YEAR(A77) -> 2024 | I77: =MONTH(A77) -> 1 | J77: =IF(F77="net sales",E77, IF(F77="cogs",-E77, IF(OR(F77="marketing",F77="overhead",F77="payroll",F77="interest","amortization"),-E77,0))) -> -1332.93
A78: 45302 | B78: marketing | C78: NA | D78: NA | E78: 99.94 | F78: =IFERROR(LEFT(B78,FIND(":",B78)-1),B78) -> marketing | G78: NA | H78: =YEAR(A78) -> 2024 | I78: =MONTH(A78) -> 1 | J78: =IF(F78="net sales",E78, IF(F78="cogs",-E78, IF(OR(F78="marketing",F78="overhead",F78="payroll",F78="interest","amortization"),-E78,0))) -> -99.94
A79: 45302 | B79: net sales:product 1 | C79: 9.99 | D79: 21 | E79: 209.79 | F79: =IFERROR(LEFT(B79,FIND(":",B79)-1),B79) -> net sales | G79: =IFERROR(RIGHT(B79,LEN(B79)-FIND(":",B79)),"") -> product 1 | H79: =YEAR(A79) -> 2024 | I79: =MONTH(A79) -> 1 | J79: =IF(F79="net sales",E79, IF(F79="cogs",-E79, IF(OR(F79="marketing",F79="overhead",F79="payroll",F79="interest","amortization"),-E79,0))) -> 209.79
A80: 45302 | B80: net sales:product 2 | C80: 24.99 | D80: 2 | E80: 49.98 | F80: =IFERROR(LEFT(B80,FIND(":",B80)-1),B80) -> net sales | G80: =IFERROR(RIGHT(B80,LEN(B80)-FIND(":",B80)),"") -> product 2 | H80: =YEAR(A80) -> 2024 | I80: =MONTH(A80) -> 1 | J80: =IF(F80="net sales",E80, IF(F80="cogs",-E80, IF(OR(F80="marketing",F80="overhead",F80="payroll",F80="interest","amortization"),-E80,0))) -> 49.98
A81: 45302 | B81: net sales:product 3 | C81: 12.49 | D81: 157 | E81: 1960.93 | F81: =IFERROR(LEFT(B81,FIND(":",B81)-1),B81) -> net sales | G81: =IFERROR(RIGHT(B81,LEN(B81)-FIND(":",B81)),"") -> product 3 | H81: =YEAR(A81) -> 2024 | I81: =MONTH(A81) -> 1 | J81: =IF(F81="net sales",E81, IF(F81="cogs",-E81, IF(OR(F81="marketing",F81="overhead",F81="payroll",F81="interest","amortization"),-E81,0))) -> 1960.93
A82: 45303 | B82: cogs:product 1 | C82: 5.99 | D82: 58 | E82: 347.42 | F82: =IFERROR(LEFT(B82,FIND(":",B82)-1),B82) -> cogs | G82: =IFERROR(RIGHT(B82,LEN(B82)-FIND(":",B82)),"") -> product 1 | H82: =YEAR(A82) -> 2024 | I82: =MONTH(A82) -> 1 | J82: =IF(F82="net sales",E82, IF(F82="cogs",-E82, IF(OR(F82="marketing",F82="overhead",F82="payroll",F82="interest","amortization"),-E82,0))) -> -347.42
A83: 45303 | B83: cogs:product 2 | C83: 16.99 | D83: 5 | E83: 84.95 | F83: =IFERROR(LEFT(B83,FIND(":",B83)-1),B83) -> cogs | G83: =IFERROR(RIGHT(B83,LEN(B83)-FIND(":",B83)),"") -> product 2 | H83: =YEAR(A83) -> 2024 | I83: =MONTH(A83) -> 1 | J83: =IF(F83="net sales",E83, IF(F83="cogs",-E83, IF(OR(F83="marketing",F83="overhead",F83="payroll",F83="interest","amortization"),-E83,0))) -> -84.95
A84: 45303 | B84: cogs:product 3 | C84: 8.49 | D84: 17 | E84: 144.33 | F84: =IFERROR(LEFT(B84,FIND(":",B84)-1),B84) -> cogs | G84: =IFERROR(RIGHT(B84,LEN(B84)-FIND(":",B84)),"") -> product 3 | H84: =YEAR(A84) -> 2024 | I84: =MONTH(A84) -> 1 | J84: =IF(F84="net sales",E84, IF(F84="cogs",-E84, IF(OR(F84="marketing",F84="overhead",F84="payroll",F84="interest","amortization"),-E84,0))) -> -144.33
A85: 45303 | B85: marketing | C85: NA | D85: NA | E85: 100.08 | F85: =IFERROR(LEFT(B85,FIND(":",B85)-1),B85) -> marketing | G85: NA | H85: =YEAR(A85) -> 2024 | I85: =MONTH(A85) -> 1 | J85: =IF(F85="net sales",E85, IF(F85="cogs",-E85, IF(OR(F85="marketing",F85="overhead",F85="payroll",F85="interest","amortization"),-E85,0))) -> -100.08
A86: 45303 | B86: net sales:product 1 | C86: 9.99 | D86: 58 | E86: 579.42 | F86: =IFERROR(LEFT(B86,FIND(":",B86)-1),B86) -> net sales | G86: =IFERROR(RIGHT(B86,LEN(B86)-FIND(":",B86)),"") -> product 1 | H86: =YEAR(A86) -> 2024 | I86: =MONTH(A86) -> 1 | J86: =IF(F86="net sales",E86, IF(F86="cogs",-E86, IF(OR(F86="marketing",F86="overhead",F86="payroll",F86="interest","amortization"),-E86,0))) -> 579.42
A87: 45303 | B87: net sales:product 2 | C87: 24.99 | D87: 5 | E87: 124.95 | F87: =IFERROR(LEFT(B87,FIND(":",B87)-1),B87) -> net sales | G87: =IFERROR(RIGHT(B87,LEN(B87)-FIND(":",B87)),"") -> product 2 | H87: =YEAR(A87) -> 2024 | I87: =MONTH(A87) -> 1 | J87: =IF(F87="net sales",E87, IF(F87="cogs",-E87, IF(OR(F87="marketing",F87="overhead",F87="payroll",F87="interest","amortization"),-E87,0))) -> 124.95
A88: 45303 | B88: net sales:product 3 | C88: 12.49 | D88: 17 | E88: 212.33 | F88: =IFERROR(LEFT(B88,FIND(":",B88)-1),B88) -> net sales | G88: =IFERROR(RIGHT(B88,LEN(B88)-FIND(":",B88)),"") -> product 3 | H88: =YEAR(A88) -> 2024 | I88: =MONTH(A88) -> 1 | J88: =IF(F88="net sales",E88, IF(F88="cogs",-E88, IF(OR(F88="marketing",F88="overhead",F88="payroll",F88="interest","amortization"),-E88,0))) -> 212.33
A89: 45304 | B89: cogs:product 1 | C89: 5.99 | D89: 18 | E89: 107.82 | F89: =IFERROR(LEFT(B89,FIND(":",B89)-1),B89) -> cogs | G89: =IFERROR(RIGHT(B89,LEN(B89)-FIND(":",B89)),"") -> product 1 | H89: =YEAR(A89) -> 2024 | I89: =MONTH(A89) -> 1 | J89: =IF(F89="net sales",E89, IF(F89="cogs",-E89, IF(OR(F89="marketing",F89="overhead",F89="payroll",F89="interest","amortization"),-E89,0))) -> -107.82
A90: 45304 | B90: cogs:product 2 | C90: 16.99 | D90: 2 | E90: 33.98 | F90: =IFERROR(LEFT(B90,FIND(":",B90)-1),B90) -> cogs | G90: =IFERROR(RIGHT(B90,LEN(B90)-FIND(":",B90)),"") -> product 2 | H90: =YEAR(A90) -> 2024 | I90: =MONTH(A90) -> 1 | J90: =IF(F90="net sales",E90, IF(F90="cogs",-E90, IF(OR(F90="marketing",F90="overhead",F90="payroll",F90="interest","amortization"),-E90,0))) -> -33.98
A91: 45304 | B91: cogs:product 3 | C91: 8.49 | D91: 112 | E91: 950.88 | F91: =IFERROR(LEFT(B91,FIND(":",B91)-1),B91) -> cogs | G91: =IFERROR(RIGHT(B91,LEN(B91)-FIND(":",B91)),"") -> product 3 | H91: =YEAR(A91) -> 2024 | I91: =MONTH(A91) -> 1 | J91: =IF(F91="net sales",E91, IF(F91="cogs",-E91, IF(OR(F91="marketing",F91="overhead",F91="payroll",F91="interest","amortization"),-E91,0))) -> -950.88
A92: 45304 | B92: marketing | C92: NA | D92: NA | E92: 99.98 | F92: =IFERROR(LEFT(B92,FIND(":",B92)-1),B92) -> marketing | G92: NA | H92: =YEAR(A92) -> 2024 | I92: =MONTH(A92) -> 1 | J92: =IF(F92="net sales",E92, IF(F92="cogs",-E92, IF(OR(F92="marketing",F92="overhead",F92="payroll",F92="interest","amortization"),-E92,0))) -> -99.98
A93: 45304 | B93: net sales:product 1 | C93: 9.99 | D93: 18 | E93: 179.82 | F93: =IFERROR(LEFT(B93,FIND(":",B93)-1),B93) -> net sales | G93: =IFERROR(RIGHT(B93,LEN(B93)-FIND(":",B93)),"") -> product 1 | H93: =YEAR(A93) -> 2024 | I93: =MONTH(A93) -> 1 | J93: =IF(F93="net sales",E93, IF(F93="cogs",-E93, IF(OR(F93="marketing",F93="overhead",F93="payroll",F93="interest","amortization"),-E93,0))) -> 179.82
A94: 45304 | B94: net sales:product 2 | C94: 24.99 | D94: 2 | E94: 49.98 | F94: =IFERROR(LEFT(B94,FIND(":",B94)-1),B94) -> net sales | G94: =IFERROR(RIGHT(B94,LEN(B94)-FIND(":",B94)),"") -> product 2 | H94: =YEAR(A94) -> 2024 | I94: =MONTH(A94) -> 1 | J94: =IF(F94="net sales",E94, IF(F94="cogs",-E94, IF(OR(F94="marketing",F94="overhead",F94="payroll",F94="interest","amortization"),-E94,0))) -> 49.98
A95: 45304 | B95: net sales:product 3 | C95: 12.49 | D95: 112 | E95: 1398.88 | F95: =IFERROR(LEFT(B95,FIND(":",B95)-1),B95) -> net sales | G95: =IFERROR(RIGHT(B95,LEN(B95)-FIND(":",B95)),"") -> product 3 | H95: =YEAR(A95) -> 2024 | I95: =MONTH(A95) -> 1 | J95: =IF(F95="net sales",E95, IF(F95="cogs",-E95, IF(OR(F95="marketing",F95="overhead",F95="payroll",F95="interest","amortization"),-E95,0))) -> 1398.88
A96: 45305 | B96: cogs:product 1 | C96: 5.99 | D96: 81 | E96: 485.19 | F96: =IFERROR(LEFT(B96,FIND(":",B96)-1),B96) -> cogs | G96: =IFERROR(RIGHT(B96,LEN(B96)-FIND(":",B96)),"") -> product 1 | H96: =YEAR(A96) -> 2024 | I96: =MONTH(A96) -> 1 | J96: =IF(F96="net sales",E96, IF(F96="cogs",-E96, IF(OR(F96="marketing",F96="overhead",F96="payroll",F96="interest","amortization"),-E96,0))) -> -485.19
A97: 45305 | B97: cogs:product 2 | C97: 16.99 | D97: 1 | E97: 16.99 | F97: =IFERROR(LEFT(B97,FIND(":",B97)-1),B97) -> cogs | G97: =IFERROR(RIGHT(B97,LEN(B97)-FIND(":",B97)),"") -> product 2 | H97: =YEAR(A97) -> 2024 | I97: =MONTH(A97) -> 1 | J97: =IF(F97="net sales",E97, IF(F97="cogs",-E97, IF(OR(F97="marketing",F97="overhead",F97="payroll",F97="interest","amortization"),-E97,0))) -> -16.99
A98: 45305 | B98: cogs:product 3 | C98: 8.49 | D98: 134 | E98: 1137.66 | F98: =IFERROR(LEFT(B98,FIND(":",B98)-1),B98) -> cogs | G98: =IFERROR(RIGHT(B98,LEN(B98)-FIND(":",B98)),"") -> product 3 | H98: =YEAR(A98) -> 2024 | I98: =MONTH(A98) -> 1 | J98: =IF(F98="net sales",E98, IF(F98="cogs",-E98, IF(OR(F98="marketing",F98="overhead",F98="payroll",F98="interest","amortization"),-E98,0))) -> -1137.66
A99: 45305 | B99: marketing | C99: NA | D99: NA | E99: 99.9 | F99: =IFERROR(LEFT(B99,FIND(":",B99)-1),B99) -> marketing | G99: NA | H99: =YEAR(A99) -> 2024 | I99: =MONTH(A99) -> 1 | J99: =IF(F99="net sales",E99, IF(F99="cogs",-E99, IF(OR(F99="marketing",F99="overhead",F99="payroll",F99="interest","amortization"),-E99,0))) -> -99.9
A100: 45305 | B100: net sales:product 1 | C100: 9.99 | D100: 81 | E100: 809.19 | F100: =IFERROR(LEFT(B100,FIND(":",B100)-1),B100) -> net sales | G100: =IFERROR(RIGHT(B100,LEN(B100)-FIND(":",B100)),"") -> product 1 | H100: =YEAR(A100) -> 2024 | I100: =MONTH(A100) -> 1 | J100: =IF(F100="net sales",E100, IF(F100="cogs",-E100, IF(OR(F100="marketing",F100="overhead",F100="payroll",F100="interest","amortization"),-E100,0))) -> 809.19
...

Sheet P&L
A1: Ecommerce Company | M1: Calendar Year: | N1: 2024
A2: Profit & Loss Statement | B2: 1 | C2: 2 | D2: 3 | E2: 4 | F2: 5 | G2: 6 | H2: 7 | I2: 8 | J2: 9 | K2: 10 | L2: 11 | M2: 12
B3: Jan | C3: Feb | D3: Mar | E3: Apr | F3: May | G3: Jun | H3: Jul | I3: Aug | J3: Sep | K3: Oct | L3: Nov | M3: Dec | N3: Full Year
A4: REVENUE
A5: Net Sales | B5: =SUMIFS(Data!$E:$E, Data!$I:$I, $B$2, Data!$H:$H, $N$1, Data!$F:$F, "net sales") -> 67968.83 | C5: =SUMIFS(Data!$E:$E, Data!$I:$I, $C$2, Data!$H:$H, $N$1, Data!$F:$F, "net sales") -> 52966.62 | D5: =SUMIFS(Data!$E:$E, Data!$I:$I, $D$2, Data!$H:$H, $N$1, Data!$F:$F, "net sales") -> 55756.97 | E5: =SUMIFS(Data!$E:$E, Data!$I:$I, $E$2, Data!$H:$H, $N$1, Data!$F:$F, "net sales") -> 55429.22 | F5: =SUMIFS(Data!$E:$E, Data!$I:$I, $F$2, Data!$H:$H, $N$1, Data!$F:$F, "net sales") -> 57305.18 | G5: =SUMIFS(Data!$E:$E, Data!$I:$I, $G$2, Data!$H:$H, $N$1, Data!$F:$F, "net sales") -> 59788.56 | H5: =SUMIFS(Data!$E:$E, Data!$I:$I, $H$2, Data!$H:$H, $N$1, Data!$F:$F, "net sales") -> 58349.25 | I5: =SUMIFS(Data!$E:$E, Data!$I:$I, $I$2, Data!$H:$H, $N$1, Data!$F:$F, "net sales") -> 60709.84 | J5: =SUMIFS(Data!$E:$E, Data!$I:$I, $J$2, Data!$H:$H, $N$1, Data!$F:$F, "net sales") -> 65533.87 | K5: =SUMIFS(Data!$E:$E, Data!$I:$I, $K$2, Data!$H:$H, $N$1, Data!$F:$F, "net sales") -> 70224.86 | L5: =SUMIFS(Data!$E:$E, Data!$I:$I, $L$2, Data!$H:$H, $N$1, Data!$F:$F, "net sales") -> 48235.1 | M5: =SUMIFS(Data!$E:$E, Data!$I:$I, $M$2, Data!$H:$H, $N$1, Data!$F:$F, "net sales") -> 64497.17 | N5: =SUM(B5:M5) -> 716765.47
A6: COGS | B6: =SUMIFS(Data!$E:$E, Data!$I:$I, $B$2, Data!$H:$H, $N$1, Data!$F:$F, "cogs") -> 44936.83 | C6: =SUMIFS(Data!$E:$E, Data!$I:$I, $C$2, Data!$H:$H, $N$1, Data!$F:$F, "cogs") -> 35058.62 | D6: =SUMIFS(Data!$E:$E, Data!$I:$I, $D$2, Data!$H:$H, $N$1, Data!$F:$F, "cogs") -> 36936.97 | E6: =SUMIFS(Data!$E:$E, Data!$I:$I, $E$2, Data!$H:$H, $N$1, Data!$F:$F, "cogs") -> 36485.22 | F6: =SUMIFS(Data!$E:$E, Data!$I:$I, $F$2, Data!$H:$H, $N$1, Data!$F:$F, "cogs") -> 37745.18 | G6: =SUMIFS(Data!$E:$E, Data!$I:$I, $G$2, Data!$H:$H, $N$1, Data!$F:$F, "cogs") -> 39528.56 | H6: =SUMIFS(Data!$E:$E, Data!$I:$I, $H$2, Data!$H:$H, $N$1, Data!$F:$F, "cogs") -> 38461.25 | I6: =SUMIFS(Data!$E:$E, Data!$I:$I, $I$2, Data!$H:$H, $N$1, Data!$F:$F, "cogs") -> 40057.84 | J6: =SUMIFS(Data!$E:$E, Data!$I:$I, $J$2, Data!$H:$H, $N$1, Data!$F:$F, "cogs") -> 43521.87 | K6: =SUMIFS(Data!$E:$E, Data!$I:$I, $K$2, Data!$H:$H, $N$1, Data!$F:$F, "cogs") -> 46540.86 | L6: =SUMIFS(Data!$E:$E, Data!$I:$I, $L$2, Data!$H:$H, $N$1, Data!$F:$F, "cogs") -> 31699.1 | M6: =SUMIFS(Data!$E:$E, Data!$I:$I, $M$2, Data!$H:$H, $N$1, Data!$F:$F, "cogs") -> 42713.17 | N6: =SUM(B6:M6) -> 473685.47
A7: Gross Profit | B7: =B5-B6 -> 23032 | C7: =C5-C6 -> 17908 | D7: =D5-D6 -> 18820 | E7: =E5-E6 -> 18944 | F7: =F5-F6 -> 19560 | G7: =G5-G6 -> 20260 | H7: =H5-H6 -> 19888 | I7: =I5-I6 -> 20652 | ... M7: =M5-M6 -> 21784 | N7: =SUM(B7:M7) -> 243080
A8: Gross Margin | B8: =B7/B5 -> 0.33886121 | C8: =C7/C5 -> 0.33809973 | D8: =D7/D5 -> 0.33753628 | E8: =E7/E5 -> 0.3417692 | F8: =F7/F5 -> 0.3413304 | G8: =G7/G5 -> 0.33886081 | H8: =H7/H5 -> 0.34084414 | I8: =I7/I5 -> 0.3401755 | ... N8: =N7/N5 -> 0.33913464
A10: EXPENSES
A11: Payroll | B11: =SUMIFS(Data!$E:$E, Data!$I:$I, $B$2, Data!$H:$H, $N$1, Data!$F:$F, "payroll") -> 2400 | C11: =SUMIFS(Data!$E:$E, Data!$I:$I, $C$2, Data!$H:$H, $N$1, Data!$F:$F, "payroll") -> 2400 | D11: =SUMIFS(Data!$E:$E, Data!$I:$I, $D$2, Data!$H:$H, $N$1, Data!$F:$F, "payroll") -> 3600 | E11: =SUMIFS(Data!$E:$E, Data!$I:$I, $E$2, Data!$H:$H, $N$1, Data!$F:$F, "payroll") -> 2400 | F11: =SUMIFS(Data!$E:$E, Data!$I:$I, $F$2, Data!$H:$H, $N$1, Data!$F:$F, "payroll") -> 2400 | G11: =SUMIFS(Data!$E:$E, Data!$I:$I, $G$2, Data!$H:$H, $N$1, Data!$F:$F, "payroll") -> 2400 | H11: =SUMIFS(Data!$E:$E, Data!$I:$I, $H$2, Data!$H:$H, $N$1, Data!$F:$F, "payroll") -> 2400 | I11: =SUMIFS(Data!$E:$E, Data!$I:$I, $I$2, Data!$H:$H, $N$1, Data!$F:$F, "payroll") -> 3600 | J11: =SUMIFS(Data!$E:$E, Data!$I:$I, $J$2, Data!$H:$H, $N$1, Data!$F:$F, "payroll") -> 2400 | K11: =SUMIFS(Data!$E:$E, Data!$I:$I, $K$2, Data!$H:$H, $N$1, Data!$F:$F, "payroll") -> 2400 | L11: =SUMIFS(Data!$E:$E, Data!$I:$I, $L$2, Data!$H:$H, $N$1, Data!$F:$F, "payroll") -> 2400 | M11: =SUMIFS(Data!$E:$E, Data!$I:$I, $M$2, Data!$H:$H, $N$1, Data!$F:$F, "payroll") -> 2400 | N11: =SUM(B11:M11) -> 31200
A12: Overhead | B12: =SUMIFS(Data!$E:$E, Data!$I:$I, $B$2, Data!$H:$H, $N$1, Data!$F:$F, "overhead") -> 2324.25 | C12: =SUMIFS(Data!$E:$E, Data!$I:$I, $C$2, Data!$H:$H, $N$1, Data!$F:$F, "overhead") -> 2305.56 | D12: =SUMIFS(Data!$E:$E, Data!$I:$I, $D$2, Data!$H:$H, $N$1, Data!$F:$F, "overhead") -> 2303.53 | E12: =SUMIFS(Data!$E:$E, Data!$I:$I, $E$2, Data!$H:$H, $N$1, Data!$F:$F, "overhead") -> 2293.93 | F12: =SUMIFS(Data!$E:$E, Data!$I:$I, $F$2, Data!$H:$H, $N$1, Data!$F:$F, "overhead") -> 2315.6 | G12: =SUMIFS(Data!$E:$E, Data!$I:$I, $G$2, Data!$H:$H, $N$1, Data!$F:$F, "overhead") -> 2314.1 | H12: =SUMIFS(Data!$E:$E, Data!$I:$I, $H$2, Data!$H:$H, $N$1, Data!$F:$F, "overhead") -> 2314.57 | I12: =SUMIFS(Data!$E:$E, Data!$I:$I, $I$2, Data!$H:$H, $N$1, Data!$F:$F, "overhead") -> 2315.2 | J12: =SUMIFS(Data!$E:$E, Data!$I:$I, $J$2, Data!$H:$H, $N$1, Data!$F:$F, "overhead") -> 2320.04 | K12: =SUMIFS(Data!$E:$E, Data!$I:$I, $K$2, Data!$H:$H, $N$1, Data!$F:$F, "overhead") -> 2316.28 | L12: =SUMIFS(Data!$E:$E, Data!$I:$I, $L$2, Data!$H:$H, $N$1, Data!$F:$F, "overhead") -> 2312.51 | M12: =SUMIFS(Data!$E:$E, Data!$I:$I, $M$2, Data!$H:$H, $N$1, Data!$F:$F, "overhead") -> 2310.94 | N12: =SUM(B12:M12) -> 27746.51
A13: Marketing | B13: =SUMIFS(Data!$E:$E, Data!$I:$I, $B$2, Data!$H:$H, $N$1, Data!$F:$F, "marketing") -> 3099.34 | C13: =SUMIFS(Data!$E:$E, Data!$I:$I, $C$2, Data!$H:$H, $N$1, Data!$F:$F, "marketing") -> 2899.9 | D13: =SUMIFS(Data!$E:$E, Data!$I:$I, $D$2, Data!$H:$H, $N$1, Data!$F:$F, "marketing") -> 3099.96 | E13: =SUMIFS(Data!$E:$E, Data!$I:$I, $E$2, Data!$H:$H, $N$1, Data!$F:$F, "marketing") -> 2999.92 | F13: =SUMIFS(Data!$E:$E, Data!$I:$I, $F$2, Data!$H:$H, $N$1, Data!$F:$F, "marketing") -> 3099.71 | G13: =SUMIFS(Data!$E:$E, Data!$I:$I, $G$2, Data!$H:$H, $N$1, Data!$F:$F, "marketing") -> 3000.36 | H13: =SUMIFS(Data!$E:$E, Data!$I:$I, $H$2, Data!$H:$H, $N$1, Data!$F:$F, "marketing") -> 3099.39 | I13: =SUMIFS(Data!$E:$E, Data!$I:$I, $I$2, Data!$H:$H, $N$1, Data!$F:$F, "marketing") -> 3100.21 | J13: =SUMIFS(Data!$E:$E, Data!$I:$I, $J$2, Data!$H:$H, $N$1, Data!$F:$F, "marketing") -> 2999.9 | K13: =SUMIFS(Data!$E:$E, Data!$I:$I, $K$2, Data!$H:$H, $N$1, Data!$F:$F, "marketing") -> 3100.18 | L13: =SUMIFS(Data!$E:$E, Data!$I:$I, $L$2, Data!$H:$H, $N$1, Data!$F:$F, "marketing") -> 3000.26 | M13: =SUMIFS(Data!$E:$E, Data!$I:$I, $M$2, Data!$H:$H, $N$1, Data!$F:$F, "marketing") -> 3099.87 | N13: =SUM(B13:M13) -> 36599
A14: Depreciation | B14: 0 | C14: 0 | D14: 0 | E14: 0 | F14: 0 | G14: 0 | H14: 0 | I14: 0 | J14: 0 | K14: 0 | L14: 0 | M14: 0 | N14: 0
A15: Amortization | B15: =SUMIFS(Data!$E:$E, Data!$I:$I, $B$2, Data!$H:$H, $N$1, Data!$F:$F, "amortization") -> 50 | C15: =SUMIFS(Data!$E:$E, Data!$I:$I, $C$2, Data!$H:$H, $N$1, Data!$F:$F, "amortization") -> 50 | D15: =SUMIFS(Data!$E:$E, Data!$I:$I, $D$2, Data!$H:$H, $N$1, Data!$F:$F, "amortization") -> 50 | E15: =SUMIFS(Data!$E:$E, Data!$I:$I, $E$2, Data!$H:$H, $N$1, Data!$F:$F, "amortization") -> 50 | F15: =SUMIFS(Data!$E:$E, Data!$I:$I, $F$2, Data!$H:$H, $N$1, Data!$F:$F, "amortization") -> 50 | G15: =SUMIFS(Data!$E:$E, Data!$I:$I, $G$2, Data!$H:$H, $N$1, Data!$F:$F, "amortization") -> 50 | H15: =SUMIFS(Data!$E:$E, Data!$I:$I, $H$2, Data!$H:$H, $N$1, Data!$F:$F, "amortization") -> 50 | I15: =SUMIFS(Data!$E:$E, Data!$I:$I, $I$2, Data!$H:$H, $N$1, Data!$F:$F, "amortization") -> 50 | J15: =SUMIFS(Data!$E:$E, Data!$I:$I, $J$2, Data!$H:$H, $N$1, Data!$F:$F, "amortization") -> 50 | K15: =SUMIFS(Data!$E:$E, Data!$I:$I, $K$2, Data!$H:$H, $N$1, Data!$F:$F, "amortization") -> 50 | L15: =SUMIFS(Data!$E:$E, Data!$I:$I, $L$2, Data!$H:$H, $N$1, Data!$F:$F, "amortization") -> 50 | M15: =SUMIFS(Data!$E:$E, Data!$I:$I, $M$2, Data!$H:$H, $N$1, Data!$F:$F, "amortization") -> 50 | N15: =SUM(B15:M15) -> 600
A16: Interest | B16: =SUMIFS(Data!$E:$E, Data!$I:$I, $B$2, Data!$H:$H, $N$1, Data!$F:$F, "interest") -> 1297 | C16: =SUMIFS(Data!$E:$E, Data!$I:$I, $C$2, Data!$H:$H, $N$1, Data!$F:$F, "interest") -> 1242.56 | D16: =SUMIFS(Data!$E:$E, Data!$I:$I, $D$2, Data!$H:$H, $N$1, Data!$F:$F, "interest") -> 1214.12 | E16: =SUMIFS(Data!$E:$E, Data!$I:$I, $E$2, Data!$H:$H, $N$1, Data!$F:$F, "interest") -> 1290.64 | F16: =SUMIFS(Data!$E:$E, Data!$I:$I, $F$2, Data!$H:$H, $N$1, Data!$F:$F, "interest") -> 1262.4 | G16: =SUMIFS(Data!$E:$E, Data!$I:$I, $G$2, Data!$H:$H, $N$1, Data!$F:$F, "interest") -> 1286.44 | H16: =SUMIFS(Data!$E:$E, Data!$I:$I, $H$2, Data!$H:$H, $N$1, Data!$F:$F, "interest") -> 1258.28 | I16: =SUMIFS(Data!$E:$E, Data!$I:$I, $I$2, Data!$H:$H, $N$1, Data!$F:$F, "interest") -> 1282.24 | J16: =SUMIFS(Data!$E:$E, Data!$I:$I, $J$2, Data!$H:$H, $N$1, Data!$F:$F, "interest") -> 1280.16 | K16: =SUMIFS(Data!$E:$E, Data!$I:$I, $K$2, Data!$H:$H, $N$1, Data!$F:$F, "interest") -> 1252.12 | L16: =SUMIFS(Data!$E:$E, Data!$I:$I, $L$2, Data!$H:$H, $N$1, Data!$F:$F, "interest") -> 1250.04 | M16: =SUMIFS(Data!$E:$E, Data!$I:$I, $M$2, Data!$H:$H, $N$1, Data!$F:$F, "interest") -> 1247.92 | N16: =SUM(B16:M16) -> 15163.92
A17: Total Expenses | B17: =SUM(B11:B16) -> 9170.59 | C17: =SUM(C11:C16) -> 8898.02 | D17: =SUM(D11:D16) -> 10267.61 | E17: =SUM(E11:E16) -> 9034.49 | F17: =SUM(F11:F16) -> 9127.71 | G17: =SUM(G11:G16) -> 9050.9 | H17: =SUM(H11:H16) -> 9122.24 | I17: =SUM(I11:I16) -> 10347.65 | ... M17: =SUM(M11:M16) -> 9108.73 | N17: =SUM(B17:M17) -> 111309.43
A19: INCOME
A20: Earnings Before Tax | B20: =B7-B17 -> 13861.41 | C20: =C7-C17 -> 9009.98 | D20: =D7-D17 -> 8552.39 | E20: =E7-E17 -> 9909.51 | F20: =F7-F17 -> 10432.29 | G20: =G7-G17 -> 11209.1 | H20: =H7-H17 -> 10765.76 | I20: =I7-I17 -> 10304.35 | ... N20: =N7-N17 -> 131770.57
A21: Taxes | B21: =B20*0.21 -> 2910.8961 | C21: =C20*0.21 -> 1892.0958 | D21: =D20*0.21 -> 1796.0019 | E21: =E20*0.21 -> 2080.9971 | F21: =F20*0.21 -> 2190.7809 | G21: =G20*0.21 -> 2353.911 | H21: =H20*0.21 -> 2260.8096 | I21: =I20*0.21 -> 2163.9135 | ... N21: =N20*0.21 -> 27671.82
A22: Net Earnings | B22: =B20-B21 -> 10950.514 | C22: =C20-C21 -> 7117.8842 | D22: =D20-D21 -> 6756.3881 | E22: =E20-E21 -> 7828.5129 | F22: =F20-F21 -> 8241.5091 | G22: =G20-G21 -> 8855.189 | H22: =H20-H21 -> 8504.9504 | I22: =I20-I21 -> 8140.4365 | ... N22: =N20-N21 -> 104098.75
A23: EBIT | B23: =B22+B16+B21 -> 15158.41 | C23: =C22+C16+C21 -> 10252.54 | D23: =D22+D16+D21 -> 9766.51 | E23: =E22+E16+E21 -> 11200.15 | F23: =F22+F16+F21 -> 11694.69 | G23: =G22+G16+G21 -> 12495.54 | H23: =H22+H16+H21 -> 12024.04 | I23: =I22+I16+I21 -> 11586.59 | ... N23: =N22+N16+N21 -> 146934.49
A24: EBITDA | B24: =B22+B16+B21+B14+B15 -> 15208.41 | C24: =C22+C16+C21+C14+C15 -> 10302.54 | D24: =D22+D16+D21+D14+D15 -> 9816.51 | E24: =E22+E16+E21+E14+E15 -> 11250.15 | F24: =F22+F16+F21+F14+F15 -> 11744.69 | G24: =G22+G16+G21+G14+G15 -> 12545.54 | H24: =H22+H16+H21+H14+H15 -> 12074.04 | I24: =I22+I16+I21+I14+I15 -> 11636.59 | ... N24: =N22+N16+N21+N14+N15 -> 147534.49

Sheet Products
A1: Row Labels | B1: Sum of quantity | G1: Average Daily Profit
A2: 2024 | B2: 117906 | H2: AVG 2024 | I2: AVG 2025
A3: product 1 | B3: 33816 | G3: Product 1 | H3: =AVERAGEIFS(Data!$J:$J, Data!$G:$G, "product 1", Data!$H:$H, 2024) -> 362.92725 | I3: =AVERAGEIFS(Data!$J:$J, Data!$G:$G, "product 1", Data!$H:$H, 2025) -> 422.95264
A4: product 2 | B4: 3634 | G4: Product 2 | H4: =AVERAGEIFS(Data!$J:$J, Data!$G:$G, "product 2", Data!$H:$H, 2024) -> 63.48918 | I4: =AVERAGEIFS(Data!$J:$J, Data!$G:$G, "product 2", Data!$H:$H, 2025) -> 83.365945
A5: product 3 | B5: 80456 | G5: Product 3 | H5: =AVERAGEIFS(Data!$J:$J, Data!$G:$G, "product 3", Data!$H:$H, 2024) -> 62.904454 | I5: =AVERAGEIFS(Data!$J:$J, Data!$G:$G, "product 3", Data!$H:$H, 2025) -> 38.914192
A6: 2025 | B6: 129514
A7: product 1 | B7: 37844
A8: product 2 | B8: 2798
A9: product 3 | B9: 88872
A10: Grand Total | B10: 247420
A12: Growth
B13: Units 2024 | C13: Units 2025 | D13: Growth | E13: Growth %
A14: Product 1 | B14: =GETPIVOTDATA("quantity",$A$1,"product","product 1","year",2024) -> 33816 | C14: =GETPIVOTDATA("quantity",$A$1,"product","product 1","year",2025) -> 37844 | D14: =C14-B14 -> 4028 | E14: =D14/B14 -> 0.11911521
A15: Product 2 | B15: =GETPIVOTDATA("quantity",$A$1,"product","product 2","year",2024) -> 3634 | C15: =GETPIVOTDATA("quantity",$A$1,"product","product 2","year",2025) -> 2798 | D15: =C15-B15 -> -836 | E15: =D15/B15 -> -0.23004953
A16: Product 3 | B16: =GETPIVOTDATA("quantity",$A$1,"product","product 3","year",2024) -> 80456 | C16: =GETPIVOTDATA("quantity",$A$1,"product","product 3","year",2025) -> 88872 | D16: =C16-B16 -> 8416 | E16: =D16/B16 -> 0.10460376
A17: All Products | B17: =GETPIVOTDATA("quantity",$A$1,"year",2024) -> 117906 | C17: =GETPIVOTDATA("quantity",$A$1,"year",2025) -> 129514 | D17: =C17-B17 -> 11608 | E17: =D17/B17 -> 0.098451309
A19: year | B19: product | C19: Max of quantity
A20: 2024 | C20: 249
B21: product 1 | C21: 99
B22: product 2 | C22: 10
B23: product 3 | C23: 249
A24: 2025 | C24: 273
B25: product 1 | C25: 103
B26: product 2 | C26: 9
B27: product 3 | C27: 273
A28: Grand Total | C28: 273
A30: Max Units Per Day
B31: Max 2024 | C31: Max 2025 | D31: Difference
A32: Product 1 | B32: =GETPIVOTDATA("quantity",$A$19,"product","product 1","year",2024) -> 99 | C32: =GETPIVOTDATA("quantity",$A$19,"product","product 1","year",2025) -> 103 | D32: =C32-B32 -> 4
A33: Product 2 | B33: =GETPIVOTDATA("quantity",$A$19,"product","product 2","year",2024) -> 10 | C33: =GETPIVOTDATA("quantity",$A$19,"product","product 2","year",2025) -> 9 | D33: =C33-B33 -> -1
A34: Product 3 | B34: =GETPIVOTDATA("quantity",$A$19,"product","product 3","year",2024) -> 249 | C34: =GETPIVOTDATA("quantity",$A$19,"product","product 3","year",2025) -> 273 | D34: =C34-B34 -> 24

Sheet Charts

Sheet Analysis
A1: category | B1: net sales
A3: Sum of total | B3: Column Labels
A4: Row Labels | B4: 2024 | C4: 2025 | D4: Grand Total
A5: 1 | B5: 67968.83 | C5: 63068.1 | D5: 131036.93
A6: 2 | B6: 52966.62 | C6: 50910.72 | D6: 103877.34
A7: 3 | B7: 55756.97 | C7: 63397.1 | D7: 119154.07
A8: 4 | B8: 55429.22 | C8: 65832.4 | D8: 121261.62
A9: 5 | B9: 57305.18 | C9: 64291.96 | D9: 121597.14
A10: 6 | B10: 59788.56 | C10: 56920.56 | D10: 116709.12
A11: 7 | B11: 58349.25 | C11: 73444.38 | D11: 131793.63
A12: 8 | B12: 60709.84 | C12: 62057.77 | D12: 122767.61
A13: 9 | B13: 65533.87 | C13: 66704.1 | D13: 132237.97
A14: 10 | B14: 70224.86 | C14: 72541.66 | D14: 142766.52
A15: 11 | B15: 48235.1 | C15: 73094.14 | D15: 121329.24
A16: 12 | B16: 64497.17 | C16: 66734.54 | D16: 131231.71
A17: Grand Total | B17: 716765.47 | C17: 778997.43 | D17: 1495762.9

Sheet More Analysis
A1: Sum of quantity | B1: Column Labels
A2: Row Labels | B2: 2024 | C2: 2025 | D2: Grand Total
A3: 1 | B3: 11234 | C3: 10380 | D3: 21614
A4: 2 | B4: 8676 | C4: 8356 | D4: 17032
A5: 3 | B5: 9106 | C5: 10580 | D5: 19686
A6: 4 | B6: 9156 | C6: 11020 | D6: 20176
A7: 5 | B7: 9464 | C7: 10608 | D7: 20072
A8: 6 | B8: 9788 | C8: 9388 | D8: 19176
A9: 7 | B9: 9650 | C9: 12124 | D9: 21774
A10: 8 | B10: 10032 | C10: 10446 | D10: 20478
A11: 9 | B11: 10726 | C11: 11180 | D11: 21906
A12: 10 | B12: 11528 | C12: 12168 | D12: 23696
A13: 11 | B13: 7980 | C13: 12172 | D13: 20152
A14: 12 | B14: 10566 | C14: 11092 | D14: 21658
A15: Grand Total | B15: 117906 | C15: 129514 | D15: 247420
A17: Sum of quantity | B17: Column Labels
A18: Row Labels | B18: 2024 | C18: 2025 | D18: Grand Total
A19: product 1 | B19: 33816 | C19: 37844 | D19: 71660
A20: product 2 | B20: 3634 | C20: 2798 | D20: 6432
A21: product 3 | B21: 80456 | C21: 88872 | D21: 169328
A22: Grand Total | B22: 117906 | C22: 129514 | D22: 247420
